README.md
birdjson.py
setup.cfg
setup.py
birdjson.egg-info/PKG-INFO
birdjson.egg-info/SOURCES.txt
birdjson.egg-info/dependency_links.txt
birdjson.egg-info/requires.txt
birdjson.egg-info/top_level.txt