Metadata-Version: 1.1
Name: birdjson
Version: 0.20.0
Summary: Generic json to object parser for python
Home-page: https://pypi.python.org/pypi/birdjson
Author: Anthony Casagrande
Author-email: birdapi@gmail.com
License: MIT
Keywords: json birdapi
Platform: UNKNOWN
Classifier: Development Status :: 4 - Beta
Classifier: Programming Language :: Python :: 3
Classifier: Programming Language :: Python :: 3.6
Classifier: Programming Language :: Python :: 3.7
Classifier: Programming Language :: Python :: 3.8
Classifier: License :: OSI Approved :: MIT License
